RuanjianLoudongFenxiRumenZhuanti/README.md
RuanjianLoudongFenxiRumenZhuanti/__init__.py
RuanjianLoudongFenxiRumenZhuanti/__main__.py
RuanjianLoudongFenxiRumenZhuanti/file.epub
RuanjianLoudongFenxiRumenZhuanti/index.html
RuanjianLoudongFenxiRumenZhuanti/css/__init__.py
RuanjianLoudongFenxiRumenZhuanti/css/annotations.css
RuanjianLoudongFenxiRumenZhuanti/css/main.css
RuanjianLoudongFenxiRumenZhuanti/css/normalize.css
RuanjianLoudongFenxiRumenZhuanti/css/popup.css
RuanjianLoudongFenxiRumenZhuanti/font/__init__.py
RuanjianLoudongFenxiRumenZhuanti/font/fontello.eot
RuanjianLoudongFenxiRumenZhuanti/font/fontello.svg
RuanjianLoudongFenxiRumenZhuanti/font/fontello.ttf
RuanjianLoudongFenxiRumenZhuanti/font/fontello.woff
RuanjianLoudongFenxiRumenZhuanti/img/__init__.py
RuanjianLoudongFenxiRumenZhuanti/img/annotator-glyph-sprite.png
RuanjianLoudongFenxiRumenZhuanti/img/annotator-icon-sprite.png
RuanjianLoudongFenxiRumenZhuanti/img/apple-touch-icon.png
RuanjianLoudongFenxiRumenZhuanti/img/cancelfullscreen.png
RuanjianLoudongFenxiRumenZhuanti/img/close.png
RuanjianLoudongFenxiRumenZhuanti/img/fullscreen.png
RuanjianLoudongFenxiRumenZhuanti/img/loader.gif
RuanjianLoudongFenxiRumenZhuanti/img/menu-icon.png
RuanjianLoudongFenxiRumenZhuanti/img/save.png
RuanjianLoudongFenxiRumenZhuanti/img/saved.png
RuanjianLoudongFenxiRumenZhuanti/img/settings-s.png
RuanjianLoudongFenxiRumenZhuanti/img/settings.png
RuanjianLoudongFenxiRumenZhuanti/img/star.png
RuanjianLoudongFenxiRumenZhuanti/js/__init__.py
RuanjianLoudongFenxiRumenZhuanti/js/epub.js
RuanjianLoudongFenxiRumenZhuanti/js/epub.min.js
RuanjianLoudongFenxiRumenZhuanti/js/epub.min.map
RuanjianLoudongFenxiRumenZhuanti/js/hooks.min.js
RuanjianLoudongFenxiRumenZhuanti/js/hooks.min.map
RuanjianLoudongFenxiRumenZhuanti/js/reader.js
RuanjianLoudongFenxiRumenZhuanti/js/reader.js.map
RuanjianLoudongFenxiRumenZhuanti/js/reader.min.js
RuanjianLoudongFenxiRumenZhuanti/js/reader.min.map
RuanjianLoudongFenxiRumenZhuanti/js/hooks/__init__.py
ruanjian_loudong_fenxi_rumen_zhuanti-2024.3.2.0.dist-info/METADATA
ruanjian_loudong_fenxi_rumen_zhuanti-2024.3.2.0.dist-info/WHEEL
ruanjian_loudong_fenxi_rumen_zhuanti-2024.3.2.0.dist-info/entry_points.txt
ruanjian_loudong_fenxi_rumen_zhuanti-2024.3.2.0.dist-info/top_level.txt
ruanjian_loudong_fenxi_rumen_zhuanti-2024.3.2.0.dist-info/RECORD
